[
  {
    "title": "【完整高清字幕版】大摩闭门会：中韩机器人和人型机器人 260618全网独家（推荐程度：6.5星选看）",
    "channel": "小白投资笔记",
    "duration": "35:39",
    "minute": 35.6,
    "publishedAt": "2026-06-18T12:49:02.000Z",
    "mocs": [
      "MOC-人形机器人"
    ],
    "scores": {
      "时长": 20,
      "MOC匹配": 15,
      "时效": 0,
      "频道": 15,
      "个人相关": 0,
      "数据深度": 6
    },
    "total": 56
  },
  {
    "title": "大摩汽车闭门会：亚洲汽车行业月度研讨会 260618全网独家（推荐程度：6星选看）",
    "channel": "小白投资笔记",
    "duration": "34:09",
    "minute": 34.1,
    "publishedAt": "2026-06-18T11:26:17.000Z",
    "mocs": [
      "MOC-汽车智驾"
    ],
    "scores": {
      "时长": 20,
      "MOC匹配": 15,
      "时效": 0,
      "频道": 15,
      "个人相关": 0,
      "数据深度": 6
    },
    "total": 56
  },
  {
    "title": "大摩东盟峰会：人工智能时代数据中心的未来：亚太与欧洲视角 260619全网独家（推荐程度：7星选看）",
    "channel": "小白投资笔记",
    "duration": "52:38",
    "minute": 52.6,
    "publishedAt": "2026-06-19T17:00:42.000Z",
    "mocs": [
      "MOC-AI算力"
    ],
    "scores": {
      "时长": 20,
      "MOC匹配": 15,
      "时效": 0,
      "频道": 15,
      "个人相关": 0,
      "数据深度": 3
    },
    "total": 53
  },
  {
    "title": "大摩东盟峰会：赋能人工智能供应链：稀土、电力、金属——谁将胜出？260619全网独家（推荐程度：7星选看）",
    "channel": "小白投资笔记",
    "duration": "55:40",
    "minute": 55.7,
    "publishedAt": "2026-06-19T10:40:05.000Z",
    "mocs": [
      "MOC-周期资源"
    ],
    "scores": {
      "时长": 20,
      "MOC匹配": 15,
      "时效": 0,
      "频道": 15,
      "个人相关": 0,
      "数据深度": 3
    },
    "total": 53
  },
  {
    "title": "中金：AI时代与人口变局猜想 2026.6",
    "channel": "小黄的投资笔记",
    "duration": "65:01",
    "minute": 65.0,
    "publishedAt": "2026-06-18T11:21:32.000Z",
    "mocs": [
      "MOC-AI算力"
    ],
    "scores": {
      "时长": 20,
      "MOC匹配": 15,
      "时效": 0,
      "频道": 12,
      "个人相关": 0,
      "数据深度": 0
    },
    "total": 47
  },
  {
    "title": "用最好的动画为你讲解--HBM的原理",
    "channel": "Redknot-乔红",
    "duration": "16:45",
    "minute": 16.8,
    "publishedAt": "2026-06-18T11:22:58.000Z",
    "mocs": [
      "MOC-AI算力",
      "MOC-半导体国产替代"
    ],
    "scores": {
      "时长": 8,
      "MOC匹配": 25,
      "时效": 0,
      "频道": 10,
      "个人相关": 0,
      "数据深度": 0
    },
    "total": 43
  },
  {
    "title": "杰富瑞专家会：前美国国家情报官：伊朗和平协议是否已经落幕？260619全网独家（推荐程度：6.8星选看）",
    "channel": "小白投资笔记",
    "duration": "30:36",
    "minute": 30.6,
    "publishedAt": "2026-06-18T16:25:00.000Z",
    "mocs": [],
    "scores": {
      "时长": 20,
      "MOC匹配": 0,
      "时效": 0,
      "频道": 15,
      "个人相关": 0,
      "数据深度": 6
    },
    "total": 41
  },
  {
    "title": "大摩东盟峰会：东盟宏观策略：在风浪中寻找安全的东盟避风港 260618全网独家（推荐程度：7星选看）",
    "channel": "小白投资笔记",
    "duration": "46:41",
    "minute": 46.7,
    "publishedAt": "2026-06-20T08:36:08.000Z",
    "mocs": [],
    "scores": {
      "时长": 20,
      "MOC匹配": 0,
      "时效": 0,
      "频道": 15,
      "个人相关": 0,
      "数据深度": 3
    },
    "total": 38
  },
  {
    "title": "大摩东盟峰会：改革至重新评级：新加坡股市的未来 260618全网独家（推荐程度：7星选看）",
    "channel": "小白投资笔记",
    "duration": "59:25",
    "minute": 59.4,
    "publishedAt": "2026-06-20T08:07:01.000Z",
    "mocs": [],
    "scores": {
      "时长": 20,
      "MOC匹配": 0,
      "时效": 0,
      "频道": 15,
      "个人相关": 0,
      "数据深度": 3
    },
    "total": 38
  },
  {
    "title": "大摩东盟峰会：东盟在人工智能供应链中的机遇 260618全网独家（推荐程度：7星选看）",
    "channel": "小白投资笔记",
    "duration": "40:28",
    "minute": 40.5,
    "publishedAt": "2026-06-20T06:45:57.000Z",
    "mocs": [],
    "scores": {
      "时长": 20,
      "MOC匹配": 0,
      "时效": 0,
      "频道": 15,
      "个人相关": 0,
      "数据深度": 3
    },
    "total": 38
  },
  {
    "title": "大摩东盟峰会：拥抱人工智能：重塑我们的生活、工作与思维方式 260619全网独家（推荐程度：7星选看）",
    "channel": "小白投资笔记",
    "duration": "45:40",
    "minute": 45.7,
    "publishedAt": "2026-06-20T05:31:05.000Z",
    "mocs": [],
    "scores": {
      "时长": 20,
      "MOC匹配": 0,
      "时效": 0,
      "频道": 15,
      "个人相关": 0,
      "数据深度": 3
    },
    "total": 38
  },
  {
    "title": "大摩东盟峰会：东盟首选股票：能源冲击与工业超级周期中的阿尔法机会 260619全网独家（推荐程度：7星选看）",
    "channel": "小白投资笔记",
    "duration": "51:04",
    "minute": 51.1,
    "publishedAt": "2026-06-20T05:23:06.000Z",
    "mocs": [],
    "scores": {
      "时长": 20,
      "MOC匹配": 0,
      "时效": 0,
      "频道": 15,
      "个人相关": 0,
      "数据深度": 3
    },
    "total": 38
  },
  {
    "title": "大摩东盟峰会：数字轨道，实体经济：新加坡能否在数字资产竞赛中胜出 260618全网独家（推荐程度：7星选看）",
    "channel": "小白投资笔记",
    "duration": "52:21",
    "minute": 52.4,
    "publishedAt": "2026-06-19T11:06:54.000Z",
    "mocs": [],
    "scores": {
      "时长": 20,
      "MOC匹配": 0,
      "时效": 0,
      "频道": 15,
      "个人相关": 0,
      "数据深度": 3
    },
    "total": 38
  },
  {
    "title": "大摩东盟峰会：能源安全与人工智能：在多极世界中，能源与计算的交汇 260618全网独家（推荐程度：7星选看）",
    "channel": "小白投资笔记",
    "duration": "43:38",
    "minute": 43.6,
    "publishedAt": "2026-06-19T07:02:41.000Z",
    "mocs": [],
    "scores": {
      "时长": 20,
      "MOC匹配": 0,
      "时效": 0,
      "频道": 15,
      "个人相关": 0,
      "数据深度": 3
    },
    "total": 38
  },
  {
    "title": "汇丰闭门会：中国房地产解读 260618全网最快（推荐程度：4星选看）",
    "channel": "小白投资笔记",
    "duration": "08:04",
    "minute": 8.1,
    "publishedAt": "2026-06-18T06:38:22.000Z",
    "mocs": [
      "MOC-地产建材"
    ],
    "scores": {
      "时长": 3,
      "MOC匹配": 15,
      "时效": 0,
      "频道": 15,
      "个人相关": 0,
      "数据深度": 3
    },
    "total": 36
  }
]