{
  "pdf_path": "/Users/chenlei/content-factory/drafts/raw/ai-fiber-value-chain/cninfo/pdfs/300548.SH_20260624_长芯博创科技股份有限公司关于收购控股子公司少数股东股份暨与关联方共同投资实施完成的公告.PDF",
  "extracted_at": "2026-07-05T09:59:39.249572",
  "extractor_version": "1.0.0",
  "page_count": 1,
  "pages_processed": 1,
  "truncated": false,
  "file_size_kb": 79.88,
  "full_text": "=== Page 1 ===\n证券代码：300548 证券简称：长芯博创 公告编号：2026-046\n长芯博创科技股份有限公司\n关于收购控股子公司少数股东股份暨与关联方共同投资\n实施完成的公告\n本公司及董事会全体成员保证信息披露的内容真实、准确、完整，没有虚\n假记载、误导性陈述或重大遗漏。\n一、交易概述\n长芯博创科技股份有限公司（以下简称“公司”）拟以现金收购长芯盛\n（武汉）科技股份有限公司少数股东 LONGVALLEY LIGHT LIMITED持有的\n长芯盛 2.20%股份。具体内容详见公司于 2026 年 4 月 28 日在巨潮资讯网\n（http://www.cninfo.com.cn）上披露的《长芯博创科技股份有限公司关于收购\n控股子公司少数股东股份暨与关联方共同投资的公告》。\n二、进展情况\n根据《关于长芯盛（武汉）科技股份有限公司之股份转让协议》的约定，\n公司已于近日完成全部交易价款的支付，本次交易已实施完成。截至本公告披\n露日，公司持有长芯盛（武汉）科技股份有限公司62.65%股份。\n特此公告\n长芯博创科技股份有限公司董事会\n2026年6月24日",
  "tables": [],
  "table_count": 0,
  "ann_id": "1225385918",
  "ts_code": "300548.SH",
  "ann_date": "2026-06-24",
  "title": "长芯博创科技股份有限公司关于收购控股子公司少数股东股份暨与关联方共同投资实施完成的公告"
}