[{"ts_code": "002281.SZ", "end_date": "20260331", "eps": 0.3, "dt_eps": 0.3, "total_revenue_ps": 3.438, "revenue_ps": 3.438, "gross_margin": 744162056.59, "netprofit_margin": 8.3826, "roe_yearly": 9.3964, "roa_yearly": 5.374, "debt_to_assets": 43.1308, "op_yoy": 63.0576, "ebt_yoy": 61.9636, "netprofit_yoy": 59.7559}, {"ts_code": "002281.SZ", "end_date": "20260331", "eps": null, "dt_eps": null, "total_revenue_ps": 3.438, "revenue_ps": 3.438, "gross_margin": 744162056.59, "netprofit_margin": 8.3826, "roe_yearly": 9.3964, "roa_yearly": 5.374, "debt_to_assets": 43.1308, "op_yoy": null, "ebt_yoy": 61.9636, "netprofit_yoy": 59.7559}, {"ts_code": "002281.SZ", "end_date": "20251231", "eps": 1.21, "dt_eps": 1.2, "total_revenue_ps": 14.7875, "revenue_ps": 14.7875, "gross_margin": 2794926083.38, "netprofit_margin": 7.8119, "roe_yearly": 9.8593, "roa_yearly": 5.987, "debt_to_assets": 37.9218, "op_yoy": 44.8162, "ebt_yoy": 42.352, "netprofit_yoy": 43.0967}, {"ts_code": "002281.SZ", "end_date": "20250930", "eps": 0.92, "dt_eps": 0.91, "total_revenue_ps": 10.574, "revenue_ps": 10.574, "gross_margin": 1974108982.75, "netprofit_margin": 8.1689, "roe_yearly": 10.1513, "roa_yearly": 5.9659, "debt_to_assets": 39.9383, "op_yoy": 58.836, "ebt_yoy": 57.6158, "netprofit_yoy": 54.9494}, {"ts_code": "002281.SZ", "end_date": "20250630", "eps": 0.47, "dt_eps": 0.47, "total_revenue_ps": 6.498, "revenue_ps": 6.498, "gross_margin": 1180348195.71, "netprofit_margin": 6.7208, "roe_yearly": 8.0776, "roa_yearly": 4.6044, "debt_to_assets": 40.6924, "op_yoy": 72.5699, "ebt_yoy": 71.9932, "netprofit_yoy": 78.9796}, {"ts_code": "002281.SZ", "end_date": "20250630", "eps": 0.47, "dt_eps": 0.47, "total_revenue_ps": 6.498, "revenue_ps": 6.498, "gross_margin": 1180348195.71, "netprofit_margin": 6.7208, "roe_yearly": 8.0776, "roa_yearly": 4.6044, "debt_to_assets": 40.6924, "op_yoy": 72.5699, "ebt_yoy": 71.9932, "netprofit_yoy": 78.9796}, {"ts_code": "002281.SZ", "end_date": "20250331", "eps": 0.19, "dt_eps": 0.19, "total_revenue_ps": 2.8003, "revenue_ps": 2.8003, "gross_margin": 569168782.29, "netprofit_margin": 6.5859, "roe_yearly": 6.5348, "roa_yearly": 3.9468, "debt_to_assets": 37.1839, "op_yoy": 97.521, "ebt_yoy": 97.9951, "netprofit_yoy": 95.0223}]
